fastsupabased_acl/__init__.py
fastsupabased_acl-0.1.4.dist-info/METADATA
fastsupabased_acl-0.1.4.dist-info/WHEEL
fastsupabased_acl-0.1.4.dist-info/RECORD
