Metadata-Version: 2.1
Name: fastsupabased-acl
Version: 0.1.4
Summary: FastAPI Dependency for Supabase-based ACL using Supabase Roles
Author: Vinicius Mesel
Author-email: 4984147+vmesel@users.noreply.github.com
Requires-Python: >=3.11,<4.0
Classifier: Programming Language :: Python :: 3
Classifier: Programming Language :: Python :: 3.11
Classifier: Programming Language :: Python :: 3.12
Requires-Dist: fastapi (>=0.111.0,<0.112.0)
Requires-Dist: supabase (>=2.4.6,<3.0.0)
